{
    "initial_units": [
        {
            "type": "triarii",
            "count": 1,
            "faction": "ROME",
            "zone": "plain"
        },
        {
            "type": "sailors",
            "count": 1,
            "faction": "ROME",
            "zone": "port"
        },
        {
            "type": "numidians",
            "count": 1,
            "faction": "CARTHAGE",
            "zone": "east_wall"
        },
        {
            "type": "iberian_lancers",
            "count": 1,
            "faction": "CARTHAGE",
            "zone": "south_wall"
        },
        {
            "type": "balearic_slingers",
            "count": 1,
            "faction": "CARTHAGE",
            "zone": "south_wall"
        }
    ]
}